<?xml version="1.0" encoding="UTF-8" ?>
<r xmlns="http://pear.php.net/dtd/rest.release"
    xmlns:xsi="http://www.w3.org/2001/XMLSchema-instance"
    xmlns:xlink="http://www.w3.org/1999/xlink"
    xsi:schemaLocation="http://pear.php.net/dtd/rest.release
    http://pear.php.net/dtd/rest.release.xsd">
 <p xlink:href="/rest/p/mysqlnd_memcache">mysqlnd_memcache</p>
 <c>pecl.php.net</c>
 <v>1.0.0</v>
 <st>beta</st>
 <l>PHP License</l>
 <m>johannes</m>
 <s>A replication and load balancing plugin for mysqlnd</s>
 <d>A PHP extension for transparently translating SQL into requests for the MySQL InnoDB Memcached Daemon Plugin.</d>
 <da>2012-09-27 16:05:45</da>
 <n>Initial package release.</n>
 <f>30169</f>
 <g>https://pecl.php.net/get/mysqlnd_memcache-1.0.0</g>
 <x xlink:href="package.1.0.0.xml"/>
</r>