<?xml version="1.0" encoding="UTF-8" ?>
<r xmlns="http://pear.php.net/dtd/rest.release"
    xmlns:xsi="http://www.w3.org/2001/XMLSchema-instance"
    xmlns:xlink="http://www.w3.org/1999/xlink"
    xsi:schemaLocation="http://pear.php.net/dtd/rest.release
    http://pear.php.net/dtd/rest.release.xsd">
 <p xlink:href="/rest/p/rar">rar</p>
 <c>pecl.php.net</c>
 <v>0.3.0</v>
 <st>beta</st>
 <l>PHP License</l>
 <m>tony2001</m>
 <s>rar extension</s>
 <d>Rar is a powerful and effective archiver, which was 
created by Eugene Roshal and became rather popular quite fast. 
This extension gives you possibility to read Rar archives.
 
</d>
 <da>2006-06-06 04:04:58</da>
 <n>- Updated bundled unrar to version 3.6.2 (fixes compile errors with GCC4).
- Several minor fixes.</n>
 <f>125349</f>
 <g>http://pecl.php.net/get/rar-0.3.0</g>
 <x xlink:href="package.0.3.0.xml"/>
</r>