<?xml version="1.0" encoding="UTF-8" ?>
<r xmlns="http://pear.php.net/dtd/rest.release"
    xmlns:xsi="http://www.w3.org/2001/XMLSchema-instance"
    xmlns:xlink="http://www.w3.org/1999/xlink"
    xsi:schemaLocation="http://pear.php.net/dtd/rest.release
    http://pear.php.net/dtd/rest.release.xsd">
 <p xlink:href="/rest/p/yaml">yaml</p>
 <c>pecl.php.net</c>
 <v>2.0.1</v>
 <st>alpha</st>
 <l>MIT</l>
 <m>bd808</m>
 <s>YAML-1.1 parser and emitter</s>
 <d>Support for YAML 1.1 (YAML Ain't Markup Language) serialization using the
  LibYAML library.</d>
 <da>2017-07-29 21:53:40</da>
 <n>Bugs Fixed:
- relax tests to pass with 7.1.4RC1 (remicollet)
- #74799 fix memory leak in apply_filter function (gleb-svitelskiy)
- #72540 fix crash in yaml_parse_url when stream/file is empty (bd808)</n>
 <f>38474</f>
 <g>https://pecl.php.net/get/yaml-2.0.1</g>
 <x xlink:href="package.2.0.1.xml"/>
</r>