<?xml version="1.0" encoding="UTF-8" ?>
<r xmlns="http://pear.php.net/dtd/rest.release"
    xmlns:xsi="http://www.w3.org/2001/XMLSchema-instance"
    xmlns:xlink="http://www.w3.org/1999/xlink"
    xsi:schemaLocation="http://pear.php.net/dtd/rest.release
    http://pear.php.net/dtd/rest.release.xsd">
 <p xlink:href="/rest/p/apcu">apcu</p>
 <c>pecl.php.net</c>
 <v>5.1.26</v>
 <st>stable</st>
 <l>PHP License</l>
 <m>nikic</m>
 <s>APCu - APC User Cache</s>
 <d>APC User Caching</d>
 <da>2025-08-05 19:45:40</da>
 <n>- Fixed hang introduced in apcu 5.1.25, which can occur when defragmentation is triggered under
  load.
- Fixed a test on PHP 8.5.</n>
 <f>94789</f>
 <g>https://pecl.php.net/get/apcu-5.1.26</g>
 <x xlink:href="package.5.1.26.xml"/>
</r>