<?xml version="1.0" encoding="UTF-8" ?>
<r xmlns="http://pear.php.net/dtd/rest.release"
    xmlns:xsi="http://www.w3.org/2001/XMLSchema-instance"
    xmlns:xlink="http://www.w3.org/1999/xlink"
    xsi:schemaLocation="http://pear.php.net/dtd/rest.release
    http://pear.php.net/dtd/rest.release.xsd">
 <p xlink:href="/rest/p/seaslog">SeasLog</p>
 <c>pecl.php.net</c>
 <v>1.7.6</v>
 <st>stable</st>
 <l>PHP</l>
 <m>neeke</m>
 <s>A effective,fast,stable log extension for PHP.</s>
 <d>A effective,fast,stable log extension for PHP.
        - In the PHP project, for convenient record log
        - The default log directory and module configuration.
        - Specify the log directory and get the current configuration
        - Analysis of early warning framework preliminary
        - Buffer debug efficient log buffer, convenient
        - With PSR-3 Logger interface
        - Error and exception automatic logging
        - Support appender with File,TCP,UDP
        - Send to Rsyslog(TCP/UDP) with RFC5424
        - Support RequestId differentiated requests
        - Support for log template customizations</d>
 <da>2017-09-19 09:05:11</da>
 <n>- Fixed analyzerDetail bug, use grep -ai key_words.
- Fixed issue #152. Segfault in cli.</n>
 <f>90917</f>
 <g>http://pecl.php.net/get/SeasLog-1.7.6</g>
 <x xlink:href="package.1.7.6.xml"/>
</r>