{
    "active": {
        "amqp": 77,
        "apcu": 47,
        "ast": 47,
        "awscrt": 73,
        "brotli": 116,
        "couchbase": 79,
        "datadog_trace": 8,
        "ds": 9,
        "ecma_intl": 117,
        "eio": 110,
        "event": 0,
        "grpc": 28,
        "ibm_db2": 43,
        "igbinary": 26,
        "imap": 10,
        "jsonpath": 10,
        "luasandbox": 16,
        "mailparse": 129,
        "maxminddb": 27,
        "mongodb": 8,
        "mysqlnd_krb": 149,
        "openswoole": 18,
        "opentelemetry": 64,
        "pam": 97,
        "parle": 180,
        "pdo_ibm": 42,
        "pdo_sqlsrv": 20,
        "pecl_http": 88,
        "phalcon": 3,
        "pledge": 36,
        "pspell": 36,
        "redis": 67,
        "rpminfo": 49,
        "scoutapm": 27,
        "skywalking_agent": 92,
        "sqlsrv": 20,
        "swoole": 32,
        "tensor": 100,
        "xdebug": 14,
        "zephir_parser": 123,
        "zip": 44,
        "zstd": 113
    },
    "recent": {
        "apfd": 815,
        "bitset": 217,
        "bsdiff": 442,
        "crypto": 1026,
        "csv": 576,
        "dbase": 790,
        "decimal": 1045,
        "dio": 702,
        "ev": 775,
        "excimer": 290,
        "fann": 725,
        "gearman": 1076,
        "geospatial": 504,
        "gmagick": 1050,
        "gnupg": 727,
        "handlebars": 396,
        "ice": 312,
        "imagick": 716,
        "immutable_cache": 392,
        "ion": 577,
        "ip2location": 200,
        "ip2proxy": 514,
        "json_post": 827,
        "krb5": 321,
        "leveldb": 1043,
        "lzf": 723,
        "memcache": 243,
        "memcached": 644,
        "memprof": 720,
        "msgpack": 210,
        "mustache": 397,
        "mysql_xdevapi": 521,
        "nsq": 832,
        "oci8": 253,
        "opencensus": 932,
        "parallel": 426,
        "pcov": 738,
        "pcsc": 1041,
        "pdo_informix": 707,
        "pdo_taos": 478,
        "php_trie": 583,
        "pkcs11": 186,
        "pq": 200,
        "ps": 820,
        "psr": 747,
        "quickhash": 528,
        "rdkafka": 544,
        "rnp": 268,
        "rrd": 980,
        "runkit7": 502,
        "scrypt": 235,
        "sdl": 524,
        "sdl_image": 652,
        "sdl_mixer": 653,
        "sdl_ttf": 513,
        "seasclick": 308,
        "seaslog": 1074,
        "seassnowflake": 859,
        "selinux": 736,
        "simdjson": 436,
        "simple_kafka_client": 877,
        "skywalking": 547,
        "smbclient": 256,
        "solr": 414,
        "ssh2": 252,
        "stomp": 577,
        "sync": 183,
        "teds": 413,
        "timezonedb": 275,
        "trader": 1075,
        "uopz": 801,
        "uploadprogress": 819,
        "uv": 194,
        "var_representation": 438,
        "varnish": 1075,
        "vld": 469,
        "weakreference_bc": 721,
        "win32service": 420,
        "xdiff": 583,
        "xhprof": 380,
        "xlswriter": 228,
        "xmldiff": 1075,
        "yac": 741,
        "yaconf": 589,
        "yaf": 588,
        "yaml": 298,
        "yar": 590,
        "yaz": 494,
        "zookeeper": 295
    },
    "unmaintained": {
        "amfext": -1,
        "apd": -1,
        "apn": -1,
        "archive": -1,
        "ares": -1,
        "bbcode": -1,
        "bcompiler": -1,
        "big_int": -1,
        "binpack": -1,
        "blenc": -1,
        "cairo": -1,
        "chdb": -1,
        "coin_acceptor": -1,
        "colorer": -1,
        "crack": -1,
        "cyrus": -1,
        "dbdo": -1,
        "dbplus": -1,
        "dbus": -1,
        "dbx": -1,
        "dom_varimport": -1,
        "drizzle": -1,
        "dtrace": -1,
        "enchant": -1,
        "fam": -1,
        "ffi": -1,
        "freeimage": -1,
        "fribidi": -1,
        "funcall": -1,
        "fuse": -1,
        "gdchart": -1,
        "gupnp": -1,
        "haru": -1,
        "hash": -1,
        "hidef": -1,
        "html_parse": -1,
        "htscanner": -1,
        "huffman": -1,
        "id3": -1,
        "imlib2": -1,
        "inclued": -1,
        "ingres": -1,
        "intl": -1,
        "ircclient": -1,
        "jsond": -1,
        "judy": -1,
        "kadm5": -1,
        "ktaglib": -1,
        "lapack": -1,
        "lchash": -1,
        "libevent": -1,
        "maxdb": -1,
        "mcrypt": 10,
        "mcve": -1,
        "mdbtools": -1,
        "memsession": -1,
        "memtrack": -1,
        "mono": -1,
        "mysqlnd_memcache": -1,
        "mysqlnd_ms": -1,
        "mysqlnd_qc": -1,
        "mysqlnd_uh": -1,
        "ncurses": -1,
        "net_gopher": -1,
        "netools": -1,
        "newt": -1,
        "odbtp": -1,
        "oggvorbis": -1,
        "opendirectory": -1,
        "operator": -1,
        "optimizer": -1,
        "panda": -1,
        "paradox": -1,
        "parse_tree": -1,
        "parsekit": -1,
        "pdflib": -1,
        "pdo_4d": -1,
        "pdo_dblib": -1,
        "pdo_firebird": -1,
        "pdo_odbc": -1,
        "pdo_pgsql": -1,
        "pdo_sqlite": -1,
        "pdo_user": -1,
        "pecl_gen": -1,
        "perl": -1,
        "phar": -1,
        "phdfs": -1,
        "phk": -1,
        "pop3": -1,
        "proctitle": -1,
        "protocolbuffers": -1,
        "python": -1,
        "qb": -1,
        "re2": -1,
        "riak": -1,
        "rpmreader": -1,
        "rsvg": -1,
        "rsync": -1,
        "sam": -1,
        "sca_sdo": -1,
        "scream": -1,
        "sphinx": -1,
        "spidermonkey": -1,
        "spl_types": -1,
        "sqlite": -1,
        "sqlite3": -1,
        "stats": -1,
        "strict": -1,
        "sundown": -1,
        "swish": -1,
        "swoole_serialize": -1,
        "tidy": -1,
        "tk": -1,
        "tokyo_tyrant": -1,
        "txforward": -1,
        "udis86": -1,
        "uri_template": -1,
        "valkyrie": -1,
        "vips": -1,
        "vpopmail": -1,
        "wbxml": -1,
        "weakref": -1,
        "win32ps": -1,
        "win32ps_dll": -1,
        "win32std": -1,
        "wincache": -1,
        "wxwidgets": -1,
        "xcommerce": -1,
        "xmlrpc": -1,
        "xmlrpci": -1,
        "xmms": -1,
        "xmp": -1,
        "xrange": -1,
        "xslcache": -1,
        "yami": -1,
        "zendopcache": -1,
        "zmq": 2888
    },
    "stale": {
        "ahocorasick": 1635,
        "aop": 4058,
        "apacheaccessor": 4140,
        "apcu_bc": 1772,
        "apm": 2509,
        "augeas": 5068,
        "base58": 1097,
        "bloomy": 5393,
        "bz2_filter": 6877,
        "cairo_wrapper": 5753,
        "cassandra": 2327,
        "cld": 4427,
        "clips": 6968,
        "clucene": 6606,
        "cmark": 1677,
        "componere": 1177,
        "courierauth": 6227,
        "crack_dll": 6673,
        "cubrid": 2338,
        "cvsclient": 7197,
        "cybermut": 7514,
        "dazuko": 7023,
        "docblock": 6393,
        "doublemetaphone": 3524,
        "druid": 2071,
        "ecasound": 7649,
        "env": 2918,
        "esmtp": 7010,
        "expect": 1445,
        "framegrab": 5051,
        "functional": 4394,
        "gender": 3250,
        "geoip": 2688,
        "graphdat": 3310,
        "hdr_histogram": 2690,
        "hprose": 1377,
        "hrtime": 2548,
        "http_message": 1221,
        "idn": 5470,
        "ims": 6056,
        "inotify": 1106,
        "intercept": 4214,
        "isis": 7069,
        "jsmin": 2165,
        "jsonc": 2753,
        "jsonnet": 2042,
        "libsodium": 1117,
        "lua": 1389,
        "markdown": 4329,
        "mcrypt_filter": 6879,
        "memoize": 3844,
        "meta": 4497,
        "mogilefs": 2900,
        "molten": 2325,
        "mosquitto": 2481,
        "mqseries": 2358,
        "mysqlnd_azure": 1240,
        "oauth": 1197,
        "ocal": 5831,
        "openal": 1592,
        "opengl": 1924,
        "orng": 1100,
        "params": 5890,
        "pcs": 1292,
        "pdo_cubrid": 2219,
        "pdo_sqlanywhere": 2491,
        "perforce": 5001,
        "propro": 2090,
        "protobuf": 1256,
        "qqwry": 5512,
        "radius": 2873,
        "raphf": 1526,
        "rar": 1117,
        "ref": 2121,
        "request": 1359,
        "sandbox": 1562,
        "sasl": 7276,
        "shape": 5212,
        "spplus": 7719,
        "spread": 5545,
        "ssdeep": 2138,
        "stackdriver_debugger": 2122,
        "statgrab": 6260,
        "stem": 4295,
        "svm": 1956,
        "svn": 1474,
        "syck": 5518,
        "taint": 1358,
        "tcc": 5726,
        "tclink": 7414,
        "tcpwrap": 2474,
        "tdb": 5733,
        "termbox": 2675,
        "textcat": 4366,
        "timecop": 2227,
        "trace": 2481,
        "translit": 1184,
        "tvision": 6824,
        "ui": 2613,
        "uuid": 1178,
        "v8": 2128,
        "v8js": 1225,
        "wasm": 1589,
        "winbinder": 6412,
        "xattr": 1344,
        "xxtea": 2914,
        "yp": 3518,
        "zeroconf": 6669,
        "zlib_filter": 7100
    },
    "zero-releases": {
        "apc": -1,
        "automap": -1,
        "axis2": -1,
        "bcgen": -1,
        "bz2": -1,
        "classkit": -1,
        "coherence": -1,
        "cpdf": -1,
        "cybercash": -1,
        "daffodildb": -1,
        "date_time": -1,
        "domxml": -1,
        "ereg": -1,
        "fileinfo": -1,
        "filepro": -1,
        "filter": -1,
        "flitetts": -1,
        "hwapi": -1,
        "informix": -1,
        "interbase": -1,
        "json": -1,
        "libvirt": -1,
        "llvm": -1,
        "ming": -1,
        "mnogosearch": -1,
        "mongo": -1,
        "msession": -1,
        "mysql": -1,
        "mysqlnd_ngen": -1,
        "namazu": -1,
        "notes": -1,
        "opencv": -1,
        "ovrimos": -1,
        "pango": -1,
        "pdo": -1,
        "pdo_mysql": -1,
        "pdo_oci": -1,
        "pdo_xml": -1,
        "php_xcb": -1,
        "phpscript": -1,
        "postparser": -1,
        "preprocessor": -1,
        "printer": -1,
        "pthreads": -1,
        "recode": -1,
        "runkit": -1,
        "session_mysql": -1,
        "spl": -1,
        "sqlanywhere": -1,
        "threads": -1,
        "unicode": -1,
        "unicodestring": -1,
        "w32api": -1,
        "wddx": -1,
        "wkhtmltox": -1,
        "xmlreader": -1,
        "xmlwriter": -1
    }
}