{
    "active": {
        "amqp": 97,
        "apcu": 67,
        "ast": 67,
        "awscrt": 93,
        "brotli": 136,
        "couchbase": 99,
        "datadog_trace": 0,
        "ds": 29,
        "ecma_intl": 137,
        "eio": 130,
        "event": 20,
        "grpc": 48,
        "ibm_db2": 63,
        "igbinary": 46,
        "imap": 14,
        "jsonpath": 9,
        "luasandbox": 36,
        "mailparse": 149,
        "maxminddb": 47,
        "mongodb": 28,
        "mysqlnd_krb": 169,
        "openswoole": 38,
        "opentelemetry": 84,
        "pam": 117,
        "pdo_ibm": 62,
        "pdo_sqlsrv": 40,
        "pecl_http": 108,
        "phalcon": 8,
        "pledge": 56,
        "pspell": 56,
        "redis": 87,
        "rpminfo": 69,
        "scoutapm": 47,
        "skywalking_agent": 112,
        "solr": 6,
        "sqlsrv": 40,
        "swoole": 52,
        "tensor": 120,
        "timezonedb": 16,
        "xdebug": 34,
        "zephir_parser": 143,
        "zip": 64,
        "zstd": 2
    },
    "recent": {
        "apfd": 835,
        "bitset": 237,
        "bsdiff": 462,
        "crypto": 1046,
        "csv": 596,
        "dbase": 810,
        "decimal": 1065,
        "dio": 722,
        "ev": 795,
        "excimer": 310,
        "fann": 745,
        "geospatial": 524,
        "gmagick": 1070,
        "gnupg": 747,
        "handlebars": 416,
        "ice": 332,
        "imagick": 736,
        "immutable_cache": 412,
        "ion": 597,
        "ip2location": 220,
        "ip2proxy": 534,
        "json_post": 847,
        "krb5": 341,
        "leveldb": 1063,
        "lzf": 743,
        "memcache": 263,
        "memcached": 664,
        "memprof": 740,
        "msgpack": 230,
        "mustache": 417,
        "mysql_xdevapi": 541,
        "nsq": 852,
        "oci8": 273,
        "opencensus": 952,
        "parallel": 446,
        "parle": 200,
        "pcov": 758,
        "pcsc": 1061,
        "pdo_informix": 727,
        "pdo_taos": 498,
        "php_trie": 603,
        "pkcs11": 206,
        "pq": 220,
        "ps": 840,
        "psr": 767,
        "quickhash": 548,
        "rdkafka": 564,
        "rnp": 288,
        "rrd": 1000,
        "runkit7": 522,
        "scrypt": 255,
        "sdl": 544,
        "sdl_image": 672,
        "sdl_mixer": 673,
        "sdl_ttf": 533,
        "seasclick": 328,
        "seaslog": 1094,
        "seassnowflake": 879,
        "selinux": 756,
        "simdjson": 456,
        "simple_kafka_client": 897,
        "skywalking": 567,
        "smbclient": 276,
        "ssh2": 272,
        "stomp": 597,
        "sync": 203,
        "teds": 433,
        "trader": 1095,
        "uopz": 821,
        "uploadprogress": 839,
        "uv": 214,
        "var_representation": 458,
        "varnish": 1095,
        "vld": 489,
        "weakreference_bc": 741,
        "win32service": 440,
        "xdiff": 603,
        "xhprof": 400,
        "xlswriter": 248,
        "xmldiff": 1095,
        "yac": 761,
        "yaconf": 609,
        "yaf": 608,
        "yaml": 318,
        "yar": 610,
        "yaz": 514,
        "zookeeper": 315
    },
    "unmaintained": {
        "amfext": -1,
        "apd": -1,
        "apn": -1,
        "archive": -1,
        "ares": -1,
        "bbcode": -1,
        "bcompiler": -1,
        "big_int": -1,
        "binpack": -1,
        "blenc": -1,
        "cairo": -1,
        "chdb": -1,
        "coin_acceptor": -1,
        "colorer": -1,
        "crack": -1,
        "cyrus": -1,
        "dbdo": -1,
        "dbplus": -1,
        "dbus": -1,
        "dbx": -1,
        "dom_varimport": -1,
        "drizzle": -1,
        "dtrace": -1,
        "enchant": -1,
        "fam": -1,
        "ffi": -1,
        "freeimage": -1,
        "fribidi": -1,
        "funcall": -1,
        "fuse": -1,
        "gdchart": -1,
        "gupnp": -1,
        "haru": -1,
        "hash": -1,
        "hidef": -1,
        "html_parse": -1,
        "htscanner": -1,
        "huffman": -1,
        "id3": -1,
        "imlib2": -1,
        "inclued": -1,
        "ingres": -1,
        "intl": -1,
        "ircclient": -1,
        "jsond": -1,
        "judy": -1,
        "kadm5": -1,
        "ktaglib": -1,
        "lapack": -1,
        "lchash": -1,
        "libevent": -1,
        "maxdb": -1,
        "mcrypt": 30,
        "mcve": -1,
        "mdbtools": -1,
        "memsession": -1,
        "memtrack": -1,
        "mono": -1,
        "mysqlnd_memcache": -1,
        "mysqlnd_ms": -1,
        "mysqlnd_qc": -1,
        "mysqlnd_uh": -1,
        "ncurses": -1,
        "net_gopher": -1,
        "netools": -1,
        "newt": -1,
        "odbtp": -1,
        "oggvorbis": -1,
        "opendirectory": -1,
        "operator": -1,
        "optimizer": -1,
        "panda": -1,
        "paradox": -1,
        "parse_tree": -1,
        "parsekit": -1,
        "pdflib": -1,
        "pdo_4d": -1,
        "pdo_dblib": -1,
        "pdo_firebird": -1,
        "pdo_odbc": -1,
        "pdo_pgsql": -1,
        "pdo_sqlite": -1,
        "pdo_user": -1,
        "pecl_gen": -1,
        "perl": -1,
        "phar": -1,
        "phdfs": -1,
        "phk": -1,
        "pop3": -1,
        "proctitle": -1,
        "protocolbuffers": -1,
        "python": -1,
        "qb": -1,
        "re2": -1,
        "riak": -1,
        "rpmreader": -1,
        "rsvg": -1,
        "rsync": -1,
        "sam": -1,
        "sca_sdo": -1,
        "scream": -1,
        "sphinx": -1,
        "spidermonkey": -1,
        "spl_types": -1,
        "sqlite": -1,
        "sqlite3": -1,
        "stats": -1,
        "strict": -1,
        "sundown": -1,
        "swish": -1,
        "swoole_serialize": -1,
        "tidy": -1,
        "tk": -1,
        "tokyo_tyrant": -1,
        "txforward": -1,
        "udis86": -1,
        "uri_template": -1,
        "valkyrie": -1,
        "vips": -1,
        "vpopmail": -1,
        "wbxml": -1,
        "weakref": -1,
        "win32ps": -1,
        "win32ps_dll": -1,
        "win32std": -1,
        "wincache": -1,
        "wxwidgets": -1,
        "xcommerce": -1,
        "xmlrpc": -1,
        "xmlrpci": -1,
        "xmms": -1,
        "xmp": -1,
        "xrange": -1,
        "xslcache": -1,
        "yami": -1,
        "zendopcache": -1,
        "zmq": 2908
    },
    "stale": {
        "ahocorasick": 1655,
        "aop": 4078,
        "apacheaccessor": 4160,
        "apcu_bc": 1792,
        "apm": 2529,
        "augeas": 5088,
        "base58": 1117,
        "bloomy": 5413,
        "bz2_filter": 6897,
        "cairo_wrapper": 5773,
        "cassandra": 2347,
        "cld": 4447,
        "clips": 6988,
        "clucene": 6626,
        "cmark": 1697,
        "componere": 1197,
        "courierauth": 6247,
        "crack_dll": 6693,
        "cubrid": 2358,
        "cvsclient": 7217,
        "cybermut": 7534,
        "dazuko": 7043,
        "docblock": 6413,
        "doublemetaphone": 3544,
        "druid": 2091,
        "ecasound": 7669,
        "env": 2938,
        "esmtp": 7030,
        "expect": 1465,
        "framegrab": 5071,
        "functional": 4414,
        "gearman": 1096,
        "gender": 3270,
        "geoip": 2708,
        "graphdat": 3330,
        "hdr_histogram": 2710,
        "hprose": 1397,
        "hrtime": 2568,
        "http_message": 1241,
        "idn": 5490,
        "ims": 6076,
        "inotify": 1126,
        "intercept": 4234,
        "isis": 7089,
        "jsmin": 2185,
        "jsonc": 2773,
        "jsonnet": 2062,
        "libsodium": 1137,
        "lua": 1409,
        "markdown": 4349,
        "mcrypt_filter": 6899,
        "memoize": 3864,
        "meta": 4517,
        "mogilefs": 2920,
        "molten": 2345,
        "mosquitto": 2501,
        "mqseries": 2378,
        "mysqlnd_azure": 1260,
        "oauth": 1217,
        "ocal": 5851,
        "openal": 1612,
        "opengl": 1944,
        "orng": 1120,
        "params": 5910,
        "pcs": 1312,
        "pdo_cubrid": 2239,
        "pdo_sqlanywhere": 2511,
        "perforce": 5021,
        "propro": 2110,
        "protobuf": 1276,
        "qqwry": 5532,
        "radius": 2893,
        "raphf": 1546,
        "rar": 1137,
        "ref": 2141,
        "request": 1380,
        "sandbox": 1582,
        "sasl": 7296,
        "shape": 5232,
        "spplus": 7739,
        "spread": 5565,
        "ssdeep": 2158,
        "stackdriver_debugger": 2142,
        "statgrab": 6280,
        "stem": 4315,
        "svm": 1976,
        "svn": 1494,
        "syck": 5538,
        "taint": 1378,
        "tcc": 5746,
        "tclink": 7434,
        "tcpwrap": 2494,
        "tdb": 5753,
        "termbox": 2695,
        "textcat": 4386,
        "timecop": 2247,
        "trace": 2501,
        "translit": 1204,
        "tvision": 6844,
        "ui": 2633,
        "uuid": 1198,
        "v8": 2148,
        "v8js": 1245,
        "wasm": 1609,
        "winbinder": 6432,
        "xattr": 1364,
        "xxtea": 2934,
        "yp": 3538,
        "zeroconf": 6689,
        "zlib_filter": 7120
    },
    "zero-releases": {
        "apc": -1,
        "automap": -1,
        "axis2": -1,
        "bcgen": -1,
        "bz2": -1,
        "classkit": -1,
        "coherence": -1,
        "cpdf": -1,
        "cybercash": -1,
        "daffodildb": -1,
        "date_time": -1,
        "domxml": -1,
        "ereg": -1,
        "fileinfo": -1,
        "filepro": -1,
        "filter": -1,
        "flitetts": -1,
        "hwapi": -1,
        "informix": -1,
        "interbase": -1,
        "json": -1,
        "libvirt": -1,
        "llvm": -1,
        "ming": -1,
        "mnogosearch": -1,
        "mongo": -1,
        "msession": -1,
        "mysql": -1,
        "mysqlnd_ngen": -1,
        "namazu": -1,
        "notes": -1,
        "opencv": -1,
        "ovrimos": -1,
        "pango": -1,
        "pdo": -1,
        "pdo_mysql": -1,
        "pdo_oci": -1,
        "pdo_xml": -1,
        "php_xcb": -1,
        "phpscript": -1,
        "postparser": -1,
        "preprocessor": -1,
        "printer": -1,
        "pthreads": -1,
        "recode": -1,
        "runkit": -1,
        "session_mysql": -1,
        "spl": -1,
        "sqlanywhere": -1,
        "threads": -1,
        "unicode": -1,
        "unicodestring": -1,
        "w32api": -1,
        "wddx": -1,
        "wkhtmltox": -1,
        "xmlreader": -1,
        "xmlwriter": -1
    }
}