{
    "active": {
        "apcu": 30,
        "ast": 72,
        "awscrt": 3,
        "couchbase": 55,
        "datadog_trace": 0,
        "ev": 48,
        "event": 98,
        "excimer": 83,
        "grpc": 5,
        "igbinary": 72,
        "imap": 6,
        "krb5": 131,
        "mailparse": 17,
        "memcached": 4,
        "mongodb": 27,
        "msgpack": 26,
        "oauth": 13,
        "oci8": 89,
        "opentelemetry": 19,
        "parallel": 59,
        "phalcon": 104,
        "phpy": 46,
        "pinpoint_php": 1,
        "protobuf": 21,
        "redis": 17,
        "rpminfo": 48,
        "selinux": 13,
        "swoole": 120,
        "timezonedb": 45,
        "uuid": 13,
        "var_representation": 71,
        "win32service": 35,
        "xdebug": 17,
        "xhprof": 103,
        "xlswriter": 47,
        "xpass": 25,
        "yaf": 119,
        "yaml": 14,
        "yar": 118,
        "zephir_parser": 140,
        "zip": 25
    },
    "recent": {
        "amqp": 273,
        "bitset": 514,
        "brotli": 264,
        "bsdiff": 740,
        "csv": 874,
        "dbase": 1088,
        "dio": 242,
        "ds": 307,
        "ecma_intl": 415,
        "eio": 234,
        "fann": 243,
        "gearman": 200,
        "geospatial": 802,
        "gnupg": 1025,
        "handlebars": 694,
        "hdr_histogram": 181,
        "ibm_db2": 341,
        "ice": 610,
        "imagick": 1014,
        "immutable_cache": 690,
        "ion": 874,
        "ip2location": 497,
        "ip2proxy": 812,
        "jsonpath": 287,
        "luasandbox": 313,
        "lzf": 1021,
        "maxminddb": 325,
        "memcache": 540,
        "memprof": 1018,
        "mustache": 695,
        "mysql_xdevapi": 818,
        "mysqlnd_krb": 446,
        "openswoole": 316,
        "pam": 395,
        "parle": 478,
        "pcov": 1036,
        "pdo_ibm": 340,
        "pdo_informix": 1004,
        "pdo_sqlsrv": 264,
        "pdo_taos": 776,
        "pecl_http": 385,
        "php_trie": 880,
        "pkcs11": 484,
        "pledge": 334,
        "pq": 259,
        "pspell": 333,
        "psr": 1045,
        "quickhash": 825,
        "rdkafka": 842,
        "rnp": 566,
        "runkit7": 800,
        "scoutapm": 325,
        "scrypt": 533,
        "sdl": 822,
        "sdl_image": 950,
        "sdl_mixer": 951,
        "sdl_ttf": 811,
        "seasclick": 605,
        "simdjson": 733,
        "skywalking": 844,
        "skywalking_agent": 390,
        "smbclient": 554,
        "solr": 284,
        "sqlsrv": 264,
        "ssh2": 255,
        "stomp": 874,
        "sync": 481,
        "teds": 711,
        "tensor": 220,
        "uv": 492,
        "vld": 766,
        "weakreference_bc": 1019,
        "xdiff": 881,
        "yac": 1038,
        "yaconf": 887,
        "yaz": 791,
        "zookeeper": 593,
        "zstd": 267
    },
    "unmaintained": {
        "amfext": -1,
        "apd": -1,
        "apn": -1,
        "archive": -1,
        "ares": -1,
        "bbcode": -1,
        "bcompiler": -1,
        "big_int": -1,
        "binpack": -1,
        "blenc": -1,
        "cairo": -1,
        "chdb": -1,
        "coin_acceptor": -1,
        "colorer": -1,
        "crack": -1,
        "cyrus": -1,
        "dbdo": -1,
        "dbplus": -1,
        "dbus": -1,
        "dbx": -1,
        "dom_varimport": -1,
        "drizzle": -1,
        "dtrace": -1,
        "enchant": -1,
        "fam": -1,
        "ffi": -1,
        "freeimage": -1,
        "fribidi": -1,
        "funcall": -1,
        "fuse": -1,
        "gdchart": -1,
        "gupnp": -1,
        "haru": -1,
        "hash": -1,
        "hidef": -1,
        "html_parse": -1,
        "htscanner": -1,
        "huffman": -1,
        "id3": -1,
        "imlib2": -1,
        "inclued": -1,
        "ingres": -1,
        "intl": -1,
        "ircclient": -1,
        "jsond": -1,
        "judy": -1,
        "kadm5": -1,
        "ktaglib": -1,
        "lapack": -1,
        "lchash": -1,
        "libevent": -1,
        "maxdb": -1,
        "mcrypt": 307,
        "mcve": -1,
        "mdbtools": -1,
        "memsession": -1,
        "memtrack": -1,
        "mono": -1,
        "mysqlnd_memcache": -1,
        "mysqlnd_ms": -1,
        "mysqlnd_qc": -1,
        "mysqlnd_uh": -1,
        "ncurses": -1,
        "net_gopher": -1,
        "netools": -1,
        "newt": -1,
        "odbtp": -1,
        "oggvorbis": -1,
        "opendirectory": -1,
        "operator": -1,
        "optimizer": -1,
        "panda": -1,
        "paradox": -1,
        "parse_tree": -1,
        "parsekit": -1,
        "pdflib": -1,
        "pdo_4d": -1,
        "pdo_dblib": -1,
        "pdo_firebird": -1,
        "pdo_oci": -1,
        "pdo_odbc": -1,
        "pdo_pgsql": -1,
        "pdo_sqlite": -1,
        "pdo_user": -1,
        "pecl_gen": -1,
        "perl": -1,
        "phar": -1,
        "phdfs": -1,
        "phk": -1,
        "pop3": -1,
        "proctitle": -1,
        "protocolbuffers": -1,
        "python": -1,
        "qb": -1,
        "re2": -1,
        "riak": -1,
        "rpmreader": -1,
        "rsvg": -1,
        "rsync": -1,
        "sam": -1,
        "sca_sdo": -1,
        "scream": -1,
        "sphinx": -1,
        "spidermonkey": -1,
        "spl_types": -1,
        "sqlite": -1,
        "sqlite3": -1,
        "stats": -1,
        "strict": -1,
        "sundown": -1,
        "swish": -1,
        "swoole_serialize": -1,
        "tidy": -1,
        "tk": -1,
        "tokyo_tyrant": -1,
        "txforward": -1,
        "udis86": -1,
        "uri_template": -1,
        "valkyrie": -1,
        "vips": -1,
        "vpopmail": -1,
        "wbxml": -1,
        "weakref": -1,
        "win32ps": -1,
        "win32ps_dll": -1,
        "win32std": -1,
        "wincache": -1,
        "wxwidgets": -1,
        "xcommerce": -1,
        "xmlrpc": -1,
        "xmlrpci": -1,
        "xmms": -1,
        "xmp": -1,
        "xrange": -1,
        "xslcache": -1,
        "yami": -1,
        "zendopcache": -1,
        "zmq": 3186
    },
    "stale": {
        "ahocorasick": 1932,
        "aop": 4355,
        "apacheaccessor": 4437,
        "apcu_bc": 2070,
        "apfd": 1113,
        "apm": 2807,
        "augeas": 5365,
        "base58": 1395,
        "bloomy": 5691,
        "bz2_filter": 7175,
        "cairo_wrapper": 6051,
        "cassandra": 2625,
        "cld": 4725,
        "clips": 7266,
        "clucene": 6904,
        "cmark": 1974,
        "componere": 1474,
        "courierauth": 6524,
        "crack_dll": 6971,
        "crypto": 1324,
        "cubrid": 2636,
        "cvsclient": 7495,
        "cybermut": 7811,
        "dazuko": 7321,
        "decimal": 1722,
        "docblock": 6691,
        "doublemetaphone": 3821,
        "druid": 2368,
        "ecasound": 7947,
        "env": 3216,
        "esmtp": 7308,
        "expect": 1743,
        "framegrab": 5348,
        "functional": 4692,
        "gender": 3548,
        "geoip": 2986,
        "gmagick": 1348,
        "graphdat": 3608,
        "hprose": 1675,
        "hrtime": 2846,
        "http_message": 1518,
        "idn": 5767,
        "ims": 6353,
        "inotify": 1403,
        "intercept": 4512,
        "isis": 7367,
        "jsmin": 2463,
        "json_post": 1125,
        "jsonc": 3051,
        "jsonnet": 2339,
        "leveldb": 1341,
        "libsodium": 1415,
        "lua": 1687,
        "markdown": 4627,
        "mcrypt_filter": 7177,
        "memoize": 4142,
        "meta": 4795,
        "mogilefs": 3198,
        "molten": 2622,
        "mosquitto": 2779,
        "mqseries": 2656,
        "mysqlnd_azure": 1538,
        "nsq": 1130,
        "ocal": 6129,
        "openal": 1890,
        "opencensus": 1230,
        "opengl": 2221,
        "orng": 1398,
        "params": 6187,
        "pcs": 1590,
        "pcsc": 1339,
        "pdo_cubrid": 2517,
        "pdo_sqlanywhere": 2789,
        "perforce": 5299,
        "propro": 2387,
        "ps": 1118,
        "qqwry": 5809,
        "radius": 3171,
        "raphf": 1823,
        "rar": 1415,
        "ref": 2419,
        "request": 1657,
        "rrd": 1278,
        "sandbox": 1860,
        "sasl": 7573,
        "seaslog": 1371,
        "seassnowflake": 1156,
        "shape": 5510,
        "simple_kafka_client": 1174,
        "spplus": 8017,
        "spread": 5843,
        "ssdeep": 2436,
        "stackdriver_debugger": 2420,
        "statgrab": 6558,
        "stem": 4593,
        "svm": 2254,
        "svn": 1772,
        "syck": 5816,
        "taint": 1656,
        "tcc": 6024,
        "tclink": 7712,
        "tcpwrap": 2771,
        "tdb": 6031,
        "termbox": 2973,
        "textcat": 4664,
        "timecop": 2525,
        "trace": 2779,
        "trader": 1373,
        "translit": 1481,
        "tvision": 7122,
        "ui": 2911,
        "uopz": 1098,
        "uploadprogress": 1117,
        "v8": 2426,
        "v8js": 1522,
        "varnish": 1373,
        "wasm": 1887,
        "winbinder": 6710,
        "xattr": 1641,
        "xmldiff": 1373,
        "xxtea": 3212,
        "yp": 3816,
        "zeroconf": 6967,
        "zlib_filter": 7398
    },
    "zero-releases": {
        "apc": -1,
        "automap": -1,
        "axis2": -1,
        "bcgen": -1,
        "bz2": -1,
        "classkit": -1,
        "coherence": -1,
        "cpdf": -1,
        "cybercash": -1,
        "daffodildb": -1,
        "date_time": -1,
        "domxml": -1,
        "ereg": -1,
        "fileinfo": -1,
        "filepro": -1,
        "filter": -1,
        "flitetts": -1,
        "hwapi": -1,
        "informix": -1,
        "interbase": -1,
        "json": -1,
        "libvirt": -1,
        "llvm": -1,
        "ming": -1,
        "mnogosearch": -1,
        "mongo": -1,
        "msession": -1,
        "mysql": -1,
        "mysqlnd_ngen": -1,
        "namazu": -1,
        "notes": -1,
        "opencv": -1,
        "ovrimos": -1,
        "pango": -1,
        "pdo": -1,
        "pdo_mysql": -1,
        "pdo_xml": -1,
        "php_xcb": -1,
        "phpscript": -1,
        "postparser": -1,
        "preprocessor": -1,
        "printer": -1,
        "pthreads": -1,
        "recode": -1,
        "runkit": -1,
        "session_mysql": -1,
        "spl": -1,
        "sqlanywhere": -1,
        "threads": -1,
        "unicode": -1,
        "unicodestring": -1,
        "w32api": -1,
        "wddx": -1,
        "wkhtmltox": -1,
        "xmlreader": -1,
        "xmlwriter": -1
    }
}