{
    "active": {
        "apcu": 33,
        "ast": 75,
        "awscrt": 6,
        "couchbase": 2,
        "datadog_trace": 3,
        "ev": 51,
        "event": 101,
        "excimer": 86,
        "grpc": 8,
        "igbinary": 75,
        "imap": 9,
        "krb5": 134,
        "mailparse": 20,
        "memcached": 7,
        "mongodb": 30,
        "msgpack": 29,
        "oauth": 16,
        "oci8": 92,
        "opentelemetry": 22,
        "parallel": 62,
        "phalcon": 107,
        "phpy": 49,
        "pinpoint_php": 2,
        "protobuf": 1,
        "rdkafka": 0,
        "redis": 20,
        "rpminfo": 51,
        "selinux": 16,
        "swoole": 123,
        "timezonedb": 48,
        "uuid": 16,
        "var_representation": 74,
        "win32service": 0,
        "xdebug": 20,
        "xhprof": 106,
        "xlswriter": 50,
        "xpass": 28,
        "yaf": 122,
        "yaml": 17,
        "yar": 121,
        "zephir_parser": 143,
        "zip": 28
    },
    "recent": {
        "amqp": 276,
        "bitset": 518,
        "brotli": 267,
        "bsdiff": 743,
        "csv": 877,
        "dbase": 1091,
        "dio": 245,
        "ds": 310,
        "ecma_intl": 418,
        "eio": 237,
        "fann": 246,
        "gearman": 203,
        "geospatial": 805,
        "gnupg": 1028,
        "handlebars": 697,
        "hdr_histogram": 184,
        "ibm_db2": 344,
        "ice": 613,
        "imagick": 1017,
        "immutable_cache": 693,
        "ion": 877,
        "ip2location": 500,
        "ip2proxy": 815,
        "jsonpath": 290,
        "luasandbox": 316,
        "lzf": 1024,
        "maxminddb": 328,
        "memcache": 543,
        "memprof": 1021,
        "mustache": 698,
        "mysql_xdevapi": 821,
        "mysqlnd_krb": 449,
        "openswoole": 319,
        "pam": 398,
        "parle": 481,
        "pcov": 1039,
        "pdo_ibm": 343,
        "pdo_informix": 1007,
        "pdo_sqlsrv": 267,
        "pdo_taos": 779,
        "pecl_http": 388,
        "php_trie": 883,
        "pkcs11": 487,
        "pledge": 337,
        "pq": 262,
        "pspell": 336,
        "psr": 1048,
        "quickhash": 828,
        "rnp": 569,
        "runkit7": 803,
        "scoutapm": 328,
        "scrypt": 536,
        "sdl": 825,
        "sdl_image": 953,
        "sdl_mixer": 954,
        "sdl_ttf": 814,
        "seasclick": 608,
        "simdjson": 736,
        "skywalking": 847,
        "skywalking_agent": 393,
        "smbclient": 557,
        "solr": 287,
        "sqlsrv": 267,
        "ssh2": 258,
        "stomp": 877,
        "sync": 484,
        "teds": 714,
        "tensor": 223,
        "uv": 495,
        "vld": 769,
        "weakreference_bc": 1022,
        "xdiff": 884,
        "yac": 1041,
        "yaconf": 890,
        "yaz": 794,
        "zookeeper": 596,
        "zstd": 270
    },
    "unmaintained": {
        "amfext": -1,
        "apd": -1,
        "apn": -1,
        "archive": -1,
        "ares": -1,
        "bbcode": -1,
        "bcompiler": -1,
        "big_int": -1,
        "binpack": -1,
        "blenc": -1,
        "cairo": -1,
        "chdb": -1,
        "coin_acceptor": -1,
        "colorer": -1,
        "crack": -1,
        "cyrus": -1,
        "dbdo": -1,
        "dbplus": -1,
        "dbus": -1,
        "dbx": -1,
        "dom_varimport": -1,
        "drizzle": -1,
        "dtrace": -1,
        "enchant": -1,
        "fam": -1,
        "ffi": -1,
        "freeimage": -1,
        "fribidi": -1,
        "funcall": -1,
        "fuse": -1,
        "gdchart": -1,
        "gupnp": -1,
        "haru": -1,
        "hash": -1,
        "hidef": -1,
        "html_parse": -1,
        "htscanner": -1,
        "huffman": -1,
        "id3": -1,
        "imlib2": -1,
        "inclued": -1,
        "ingres": -1,
        "intl": -1,
        "ircclient": -1,
        "jsond": -1,
        "judy": -1,
        "kadm5": -1,
        "ktaglib": -1,
        "lapack": -1,
        "lchash": -1,
        "libevent": -1,
        "maxdb": -1,
        "mcrypt": 310,
        "mcve": -1,
        "mdbtools": -1,
        "memsession": -1,
        "memtrack": -1,
        "mono": -1,
        "mysqlnd_memcache": -1,
        "mysqlnd_ms": -1,
        "mysqlnd_qc": -1,
        "mysqlnd_uh": -1,
        "ncurses": -1,
        "net_gopher": -1,
        "netools": -1,
        "newt": -1,
        "odbtp": -1,
        "oggvorbis": -1,
        "opendirectory": -1,
        "operator": -1,
        "optimizer": -1,
        "panda": -1,
        "paradox": -1,
        "parse_tree": -1,
        "parsekit": -1,
        "pdflib": -1,
        "pdo_4d": -1,
        "pdo_dblib": -1,
        "pdo_firebird": -1,
        "pdo_oci": -1,
        "pdo_odbc": -1,
        "pdo_pgsql": -1,
        "pdo_sqlite": -1,
        "pdo_user": -1,
        "pecl_gen": -1,
        "perl": -1,
        "phar": -1,
        "phdfs": -1,
        "phk": -1,
        "pop3": -1,
        "proctitle": -1,
        "protocolbuffers": -1,
        "python": -1,
        "qb": -1,
        "re2": -1,
        "riak": -1,
        "rpmreader": -1,
        "rsvg": -1,
        "rsync": -1,
        "sam": -1,
        "sca_sdo": -1,
        "scream": -1,
        "sphinx": -1,
        "spidermonkey": -1,
        "spl_types": -1,
        "sqlite": -1,
        "sqlite3": -1,
        "stats": -1,
        "strict": -1,
        "sundown": -1,
        "swish": -1,
        "swoole_serialize": -1,
        "tidy": -1,
        "tk": -1,
        "tokyo_tyrant": -1,
        "txforward": -1,
        "udis86": -1,
        "uri_template": -1,
        "valkyrie": -1,
        "vips": -1,
        "vpopmail": -1,
        "wbxml": -1,
        "weakref": -1,
        "win32ps": -1,
        "win32ps_dll": -1,
        "win32std": -1,
        "wincache": -1,
        "wxwidgets": -1,
        "xcommerce": -1,
        "xmlrpc": -1,
        "xmlrpci": -1,
        "xmms": -1,
        "xmp": -1,
        "xrange": -1,
        "xslcache": -1,
        "yami": -1,
        "zendopcache": -1,
        "zmq": 3189
    },
    "stale": {
        "ahocorasick": 1935,
        "aop": 4359,
        "apacheaccessor": 4440,
        "apcu_bc": 2073,
        "apfd": 1116,
        "apm": 2810,
        "augeas": 5368,
        "base58": 1398,
        "bloomy": 5694,
        "bz2_filter": 7178,
        "cairo_wrapper": 6054,
        "cassandra": 2628,
        "cld": 4728,
        "clips": 7269,
        "clucene": 6907,
        "cmark": 1977,
        "componere": 1478,
        "courierauth": 6527,
        "crack_dll": 6974,
        "crypto": 1327,
        "cubrid": 2639,
        "cvsclient": 7498,
        "cybermut": 7814,
        "dazuko": 7324,
        "decimal": 1725,
        "docblock": 6694,
        "doublemetaphone": 3824,
        "druid": 2371,
        "ecasound": 7950,
        "env": 3219,
        "esmtp": 7311,
        "expect": 1746,
        "framegrab": 5351,
        "functional": 4695,
        "gender": 3551,
        "geoip": 2989,
        "gmagick": 1351,
        "graphdat": 3611,
        "hprose": 1678,
        "hrtime": 2849,
        "http_message": 1521,
        "idn": 5770,
        "ims": 6356,
        "inotify": 1406,
        "intercept": 4515,
        "isis": 7370,
        "jsmin": 2466,
        "json_post": 1128,
        "jsonc": 3054,
        "jsonnet": 2342,
        "leveldb": 1344,
        "libsodium": 1418,
        "lua": 1690,
        "markdown": 4630,
        "mcrypt_filter": 7180,
        "memoize": 4145,
        "meta": 4798,
        "mogilefs": 3201,
        "molten": 2626,
        "mosquitto": 2782,
        "mqseries": 2659,
        "mysqlnd_azure": 1541,
        "nsq": 1133,
        "ocal": 6132,
        "openal": 1893,
        "opencensus": 1233,
        "opengl": 2224,
        "orng": 1401,
        "params": 6191,
        "pcs": 1593,
        "pcsc": 1342,
        "pdo_cubrid": 2520,
        "pdo_sqlanywhere": 2792,
        "perforce": 5302,
        "propro": 2390,
        "ps": 1121,
        "qqwry": 5812,
        "radius": 3174,
        "raphf": 1826,
        "rar": 1418,
        "ref": 2422,
        "request": 1660,
        "rrd": 1281,
        "sandbox": 1863,
        "sasl": 7576,
        "seaslog": 1374,
        "seassnowflake": 1159,
        "shape": 5513,
        "simple_kafka_client": 1177,
        "spplus": 8020,
        "spread": 5846,
        "ssdeep": 2439,
        "stackdriver_debugger": 2423,
        "statgrab": 6561,
        "stem": 4596,
        "svm": 2257,
        "svn": 1775,
        "syck": 5819,
        "taint": 1659,
        "tcc": 6027,
        "tclink": 7715,
        "tcpwrap": 2774,
        "tdb": 6034,
        "termbox": 2976,
        "textcat": 4667,
        "timecop": 2528,
        "trace": 2782,
        "trader": 1376,
        "translit": 1484,
        "tvision": 7125,
        "ui": 2914,
        "uopz": 1101,
        "uploadprogress": 1120,
        "v8": 2429,
        "v8js": 1525,
        "varnish": 1376,
        "wasm": 1890,
        "winbinder": 6713,
        "xattr": 1644,
        "xmldiff": 1376,
        "xxtea": 3215,
        "yp": 3819,
        "zeroconf": 6970,
        "zlib_filter": 7401
    },
    "zero-releases": {
        "apc": -1,
        "automap": -1,
        "axis2": -1,
        "bcgen": -1,
        "bz2": -1,
        "classkit": -1,
        "coherence": -1,
        "cpdf": -1,
        "cybercash": -1,
        "daffodildb": -1,
        "date_time": -1,
        "domxml": -1,
        "ereg": -1,
        "fileinfo": -1,
        "filepro": -1,
        "filter": -1,
        "flitetts": -1,
        "hwapi": -1,
        "informix": -1,
        "interbase": -1,
        "json": -1,
        "libvirt": -1,
        "llvm": -1,
        "ming": -1,
        "mnogosearch": -1,
        "mongo": -1,
        "msession": -1,
        "mysql": -1,
        "mysqlnd_ngen": -1,
        "namazu": -1,
        "notes": -1,
        "opencv": -1,
        "ovrimos": -1,
        "pango": -1,
        "pdo": -1,
        "pdo_mysql": -1,
        "pdo_xml": -1,
        "php_xcb": -1,
        "phpscript": -1,
        "postparser": -1,
        "preprocessor": -1,
        "printer": -1,
        "pthreads": -1,
        "recode": -1,
        "runkit": -1,
        "session_mysql": -1,
        "spl": -1,
        "sqlanywhere": -1,
        "threads": -1,
        "unicode": -1,
        "unicodestring": -1,
        "w32api": -1,
        "wddx": -1,
        "wkhtmltox": -1,
        "xmlreader": -1,
        "xmlwriter": -1
    }
}