{
    "active": {
        "awscrt": 110,
        "bitset": 52,
        "couchbase": 51,
        "datadog_trace": 0,
        "eio": 46,
        "excimer": 125,
        "grpc": 30,
        "ice": 147,
        "igbinary": 140,
        "ip2location": 35,
        "krb5": 156,
        "mcrypt": 138,
        "memcache": 78,
        "mongodb": 24,
        "msgpack": 45,
        "oci8": 88,
        "opentelemetry": 33,
        "parle": 15,
        "pdo_sqlsrv": 132,
        "phalcon": 28,
        "pkcs11": 21,
        "pq": 35,
        "protobuf": 5,
        "rnp": 103,
        "scrypt": 70,
        "seasclick": 143,
        "skywalking_agent": 69,
        "smbclient": 91,
        "sqlsrv": 132,
        "ssh2": 87,
        "swoole": 67,
        "sync": 18,
        "tensor": 140,
        "timezonedb": 110,
        "uv": 29,
        "xdebug": 3,
        "xlswriter": 63,
        "yaml": 133,
        "zephir_parser": 158,
        "zip": 17,
        "zookeeper": 130,
        "zstd": 79
    },
    "recent": {
        "amqp": 593,
        "apcu": 301,
        "apfd": 650,
        "ast": 341,
        "base58": 932,
        "bsdiff": 277,
        "componere": 1012,
        "crypto": 861,
        "csv": 411,
        "dbase": 625,
        "decimal": 880,
        "dio": 537,
        "ds": 580,
        "ev": 610,
        "event": 411,
        "fann": 560,
        "gearman": 911,
        "geospatial": 339,
        "gmagick": 885,
        "gnupg": 562,
        "handlebars": 231,
        "http_message": 1056,
        "ibm_db2": 318,
        "imagick": 551,
        "immutable_cache": 227,
        "inotify": 941,
        "ion": 412,
        "ip2proxy": 349,
        "json_post": 662,
        "jsonpath": 484,
        "leveldb": 878,
        "libsodium": 952,
        "luasandbox": 297,
        "lzf": 558,
        "mailparse": 305,
        "maxminddb": 636,
        "memcached": 479,
        "memprof": 555,
        "mustache": 232,
        "mysql_xdevapi": 356,
        "mysqlnd_azure": 1075,
        "nsq": 667,
        "oauth": 1032,
        "opencensus": 767,
        "openswoole": 206,
        "orng": 935,
        "pam": 543,
        "parallel": 261,
        "pcov": 573,
        "pcsc": 876,
        "pdo_ibm": 482,
        "pdo_informix": 542,
        "pdo_taos": 313,
        "pecl_http": 402,
        "php_trie": 418,
        "pledge": 282,
        "ps": 655,
        "psr": 582,
        "quickhash": 363,
        "rar": 952,
        "rdkafka": 379,
        "redis": 516,
        "rpminfo": 758,
        "rrd": 815,
        "runkit7": 337,
        "scoutapm": 215,
        "sdl": 359,
        "sdl_image": 487,
        "sdl_mixer": 488,
        "sdl_ttf": 348,
        "seaslog": 909,
        "seassnowflake": 694,
        "selinux": 571,
        "simdjson": 271,
        "simple_kafka_client": 712,
        "skywalking": 382,
        "solr": 249,
        "stomp": 412,
        "teds": 248,
        "trader": 910,
        "translit": 1019,
        "uopz": 636,
        "uploadprogress": 654,
        "uuid": 1013,
        "v8js": 1060,
        "var_representation": 273,
        "varnish": 910,
        "vld": 304,
        "weakreference_bc": 556,
        "win32service": 255,
        "xdiff": 418,
        "xhprof": 215,
        "xmldiff": 910,
        "yac": 576,
        "yaconf": 424,
        "yaf": 423,
        "yar": 425,
        "yaz": 329
    },
    "unmaintained": {
        "amfext": -1,
        "apd": -1,
        "apn": -1,
        "archive": -1,
        "ares": -1,
        "bbcode": -1,
        "bcompiler": -1,
        "big_int": -1,
        "binpack": -1,
        "blenc": -1,
        "cairo": -1,
        "chdb": -1,
        "coin_acceptor": -1,
        "colorer": -1,
        "crack": -1,
        "cyrus": -1,
        "dbdo": -1,
        "dbplus": -1,
        "dbus": -1,
        "dbx": -1,
        "dom_varimport": -1,
        "drizzle": -1,
        "dtrace": -1,
        "enchant": -1,
        "fam": -1,
        "ffi": -1,
        "freeimage": -1,
        "fribidi": -1,
        "funcall": -1,
        "fuse": -1,
        "gdchart": -1,
        "gupnp": -1,
        "haru": -1,
        "hash": -1,
        "hidef": -1,
        "html_parse": -1,
        "htscanner": -1,
        "huffman": -1,
        "id3": -1,
        "imlib2": -1,
        "inclued": -1,
        "ingres": -1,
        "intl": -1,
        "ircclient": -1,
        "jsond": -1,
        "judy": -1,
        "kadm5": -1,
        "ktaglib": -1,
        "lapack": -1,
        "lchash": -1,
        "libevent": -1,
        "maxdb": -1,
        "mcve": -1,
        "mdbtools": -1,
        "memsession": -1,
        "memtrack": -1,
        "mono": -1,
        "mysqlnd_memcache": -1,
        "mysqlnd_ms": -1,
        "mysqlnd_qc": -1,
        "mysqlnd_uh": -1,
        "ncurses": -1,
        "net_gopher": -1,
        "netools": -1,
        "newt": -1,
        "odbtp": -1,
        "oggvorbis": -1,
        "opendirectory": -1,
        "operator": -1,
        "optimizer": -1,
        "panda": -1,
        "paradox": -1,
        "parse_tree": -1,
        "parsekit": -1,
        "pdflib": -1,
        "pdo_4d": -1,
        "pdo_dblib": -1,
        "pdo_firebird": -1,
        "pdo_odbc": -1,
        "pdo_pgsql": -1,
        "pdo_sqlite": -1,
        "pdo_user": -1,
        "pecl_gen": -1,
        "perl": -1,
        "phar": -1,
        "phdfs": -1,
        "phk": -1,
        "pop3": -1,
        "proctitle": -1,
        "protocolbuffers": -1,
        "python": -1,
        "qb": -1,
        "re2": -1,
        "riak": -1,
        "rpmreader": -1,
        "rsvg": -1,
        "rsync": -1,
        "sam": -1,
        "sca_sdo": -1,
        "scream": -1,
        "sphinx": -1,
        "spidermonkey": -1,
        "spl_types": -1,
        "sqlite": -1,
        "sqlite3": -1,
        "stats": -1,
        "strict": -1,
        "sundown": -1,
        "swish": -1,
        "swoole_serialize": -1,
        "tidy": -1,
        "tk": -1,
        "tokyo_tyrant": -1,
        "txforward": -1,
        "udis86": -1,
        "uri_template": -1,
        "valkyrie": -1,
        "vips": -1,
        "vpopmail": -1,
        "wbxml": -1,
        "weakref": -1,
        "win32ps": -1,
        "win32ps_dll": -1,
        "win32std": -1,
        "wincache": -1,
        "wxwidgets": -1,
        "xcommerce": -1,
        "xmlrpc": -1,
        "xmlrpci": -1,
        "xmms": -1,
        "xmp": -1,
        "xrange": -1,
        "xslcache": -1,
        "yami": -1,
        "zendopcache": -1,
        "zmq": 2723
    },
    "stale": {
        "ahocorasick": 1470,
        "aop": 3893,
        "apacheaccessor": 3975,
        "apcu_bc": 1607,
        "apm": 2344,
        "augeas": 4903,
        "bloomy": 5228,
        "bz2_filter": 6712,
        "cairo_wrapper": 5588,
        "cassandra": 2162,
        "cld": 4262,
        "clips": 6803,
        "clucene": 6441,
        "cmark": 1512,
        "courierauth": 6062,
        "crack_dll": 6508,
        "cubrid": 2173,
        "cvsclient": 7032,
        "cybermut": 7349,
        "dazuko": 6858,
        "docblock": 6228,
        "doublemetaphone": 3359,
        "druid": 1906,
        "ecasound": 7484,
        "env": 2753,
        "esmtp": 6845,
        "expect": 1280,
        "framegrab": 4886,
        "functional": 4229,
        "gender": 3085,
        "geoip": 2523,
        "graphdat": 3145,
        "hdr_histogram": 2525,
        "hprose": 1212,
        "hrtime": 2383,
        "idn": 5305,
        "ims": 5891,
        "intercept": 4049,
        "isis": 6904,
        "jsmin": 2000,
        "jsonc": 2588,
        "jsonnet": 1877,
        "lua": 1224,
        "markdown": 4164,
        "mcrypt_filter": 6714,
        "memoize": 3679,
        "meta": 4332,
        "mogilefs": 2735,
        "molten": 2160,
        "mosquitto": 2316,
        "mqseries": 2193,
        "ocal": 5666,
        "openal": 1427,
        "opengl": 1759,
        "params": 5725,
        "pcs": 1127,
        "pdo_cubrid": 2054,
        "pdo_sqlanywhere": 2326,
        "perforce": 4836,
        "propro": 1925,
        "qqwry": 5347,
        "radius": 2708,
        "raphf": 1361,
        "ref": 1956,
        "request": 1195,
        "sandbox": 1397,
        "sasl": 7111,
        "shape": 5047,
        "spplus": 7554,
        "spread": 5380,
        "ssdeep": 1973,
        "stackdriver_debugger": 1957,
        "statgrab": 6095,
        "stem": 4130,
        "svm": 1791,
        "svn": 1309,
        "syck": 5353,
        "taint": 1193,
        "tcc": 5561,
        "tclink": 7249,
        "tcpwrap": 2309,
        "tdb": 5568,
        "termbox": 2510,
        "textcat": 4201,
        "timecop": 2062,
        "trace": 2316,
        "tvision": 6659,
        "ui": 2448,
        "v8": 1963,
        "wasm": 1424,
        "winbinder": 6247,
        "xattr": 1179,
        "xxtea": 2749,
        "yp": 3353,
        "zeroconf": 6504,
        "zlib_filter": 6935
    },
    "zero-releases": {
        "apc": -1,
        "automap": -1,
        "axis2": -1,
        "bcgen": -1,
        "bz2": -1,
        "classkit": -1,
        "coherence": -1,
        "cpdf": -1,
        "cybercash": -1,
        "daffodildb": -1,
        "date_time": -1,
        "domxml": -1,
        "ereg": -1,
        "fileinfo": -1,
        "filepro": -1,
        "filter": -1,
        "flitetts": -1,
        "hwapi": -1,
        "informix": -1,
        "interbase": -1,
        "json": -1,
        "libvirt": -1,
        "llvm": -1,
        "ming": -1,
        "mnogosearch": -1,
        "mongo": -1,
        "msession": -1,
        "mysql": -1,
        "mysqlnd_ngen": -1,
        "namazu": -1,
        "notes": -1,
        "opencv": -1,
        "ovrimos": -1,
        "pango": -1,
        "pdo": -1,
        "pdo_mysql": -1,
        "pdo_oci": -1,
        "pdo_xml": -1,
        "php_xcb": -1,
        "phpscript": -1,
        "postparser": -1,
        "preprocessor": -1,
        "printer": -1,
        "pthreads": -1,
        "recode": -1,
        "runkit": -1,
        "session_mysql": -1,
        "spl": -1,
        "sqlanywhere": -1,
        "threads": -1,
        "unicode": -1,
        "unicodestring": -1,
        "w32api": -1,
        "wddx": -1,
        "wkhtmltox": -1,
        "xmlreader": -1,
        "xmlwriter": -1
    }
}