<?xml version="1.0" encoding="UTF-8" ?>
<r xmlns="http://pear.php.net/dtd/rest.release"
    xmlns:xsi="http://www.w3.org/2001/XMLSchema-instance"
    xmlns:xlink="http://www.w3.org/1999/xlink"
    xsi:schemaLocation="http://pear.php.net/dtd/rest.release
    http://pear.php.net/dtd/rest.release.xsd">
 <p xlink:href="/rest/p/swoole">swoole</p>
 <c>pecl.php.net</c>
 <v>4.8.8</v>
 <st>stable</st>
 <l>Apache2.0</l>
 <m>tianfenghan</m>
 <s>Event-driven asynchronous and concurrent networking engine with high performance for PHP.</s>
 <d>Event-driven asynchronous and concurrent networking engine with high performance for PHP.
        - event-driven
        - coroutine
        - asynchronous non-blocking
        - multi-thread reactor
        - multi-process worker
        - multi-protocol
        - millisecond timer
        - built-in tcp/http/websocket/http2 server
        - coroutine tcp/http/websocket client
        - coroutine mysql client
        - coroutine redis client
        - coroutine read/write file system
        - coroutine dns lookup
        - support IPv4/IPv6/UnixSocket/TCP/UDP
        - support SSL/TLS encrypted transmission</d>
 <da>2022-03-16 14:38:34</da>
 <n>- Reduce SW_IPC_BUFFER_MAX_SIZE to 64k
- Respect SETTINGS_HEADER_TABLE_SIZE http2 setting (#4635)
- Fixed #4639
- Fixed http2 server NPN errors</n>
 <f>1851398</f>
 <g>https://pecl.php.net/get/swoole-4.8.8</g>
 <x xlink:href="package.4.8.8.xml"/>
</r>