<?xml version="1.0" encoding="UTF-8" ?>
<r xmlns="http://pear.php.net/dtd/rest.release"
    xmlns:xsi="http://www.w3.org/2001/XMLSchema-instance"
    xmlns:xlink="http://www.w3.org/1999/xlink"
    xsi:schemaLocation="http://pear.php.net/dtd/rest.release
    http://pear.php.net/dtd/rest.release.xsd">
 <p xlink:href="/rest/p/csv">CSV</p>
 <c>pecl.php.net</c>
 <v>0.3.1</v>
 <st>alpha</st>
 <l>PHP V3.01</l>
 <m>girgias</m>
 <s>CSV PHP extension</s>
 <d>A new and improved CSV file PHP extension which follows RFC 4180 instead of using a custom escape mechanism.

        Supports multi-bytes delimiters, enclosures, and providing a custom EOL sequence.</d>
 <da>2020-03-05 00:57:45</da>
 <n>Fix Windows compilation.
Fix package stability.
Add tests for a custom EOL sequence as nul byte.
Bundle tests with release.</n>
 <f>11790</f>
 <g>https://pecl.php.net/get/CSV-0.3.1</g>
 <x xlink:href="package.0.3.1.xml"/>
</r>