<?xml version="1.0" encoding="UTF-8" ?>
<r xmlns="http://pear.php.net/dtd/rest.release"
    xmlns:xsi="http://www.w3.org/2001/XMLSchema-instance"
    xmlns:xlink="http://www.w3.org/1999/xlink"
    xsi:schemaLocation="http://pear.php.net/dtd/rest.release
    http://pear.php.net/dtd/rest.release.xsd">
 <p xlink:href="/rest/p/mongodb">mongodb</p>
 <c>pecl.php.net</c>
 <v>1.21.1</v>
 <st>stable</st>
 <l>Apache License</l>
 <m>alcaeus</m>
 <s>MongoDB driver for PHP</s>
 <d>The purpose of this driver is to provide exceptionally thin glue between MongoDB
and PHP, implementing only fundamental and performance-critical components
necessary to build a fully-functional MongoDB driver.</d>
 <da>2025-06-13 12:26:52</da>
 <n>## What&#039;s Changed
* PHPC-2558: Update to libmongoc 1.30.3 by @alcaeus in https://github.com/mongodb/mongo-php-driver/pull/1806
* Add CODEOWNERS for 1.21+ by @alcaeus in https://github.com/mongodb/mongo-php-driver/pull/1810
* PHPC-2537 Update to newer Ubuntu version in GitHub Actions workflows by @GromNaN in https://github.com/mongodb/mongo-php-driver/pull/1814
* PHPLIB-1678: Use assume_role command before accessing secrets by @alcaeus in https://github.com/mongodb/mongo-php-driver/pull/1832
* Ignore branches that are no longer maintained when merging up by @alcaeus in https://github.com/mongodb/mongo-php-driver/pull/1838
* PHPC-2593: Update libmongoc to 1.30.5 by @alcaeus in https://github.com/mongodb/mongo-php-driver/pull/1841


**Full Changelog**: https://github.com/mongodb/mongo-php-driver/compare/1.21.0...1.21.1</n>
 <f>2156564</f>
 <g>https://pecl.php.net/get/mongodb-1.21.1</g>
 <x xlink:href="package.1.21.1.xml"/>
</r>